[{"TitleSelect":"Cars and Driving: \"20 Bộ câu hỏi & Trả lời | Mastering the Road: A Comprehensive Guide to Cars and Driving\"","index":1,"id":"comprehensive-guide-to-cars-and-driving","ListenList":["How old were you when you first learned to drive?","Maria says she was 18 when she first learned to drive.","John believes learning to drive at 16 was the perfect age.","Anna thinks starting at 20 gave her more confidence.","Was there anything difficult about learning to drive?","Maria says parking was the most challenging part.","John believes understanding traffic rules was difficult.","Anna thinks controlling the clutch in a manual car was hard.","Can you drive a car?","Maria says she can drive both manual and automatic cars.","John believes he is a skilled driver in all conditions.","Anna thinks driving is a necessary skill for independence.","Can you drive a manual shift car?","Maria says she learned to drive a manual car first.","John believes manual cars are more engaging to drive.","Anna thinks automatic cars are more convenient, but she can drive manual too.","Do you have a car?","Maria says she owns a small sedan.","John believes having a car is essential for daily commuting.","Anna thinks owning a car gives her freedom to travel anytime.","What kind of car do you have?","Maria says she has a compact car for city driving.","John believes his SUV is perfect for long trips.","Anna thinks her hybrid car is great for the environment.","Is it a standard (manual shift) or automatic shift?","Maria says her car is automatic.","John believes manual shift cars offer better control.","Anna thinks automatic cars are easier to drive in traffic.","Which do you like best, a standard or automatic shift car?","Maria says she prefers automatic for convenience.","John believes standard cars are more fun to drive.","Anna thinks automatic is better for city driving, but standard is great for the highway.","What are the advantages of owning a car?","Maria says having a car provides convenience and flexibility.","John believes owning a car saves time on commuting.","Anna thinks a car is essential for traveling long distances comfortably.","What are the disadvantages of owning a car?","Maria says maintenance and fuel costs are significant disadvantages.","John believes traffic and parking issues are major problems.","Anna thinks the environmental impact is a concern.","Are you a good driver?","Maria says she considers herself a cautious driver.","John believes he is a confident and skilled driver.","Anna thinks she is a safe and responsible driver.","Have you ever been in a car accident?","Maria says she had a minor accident last year.","John believes accidents are sometimes unavoidable despite careful driving.","Anna thinks defensive driving can prevent most accidents.","Have you ever been pulled over by the police? What happened?","Maria says she was once pulled over for speeding.","John believes following traffic rules can avoid such incidents.","Anna thinks being respectful to the police helps in such situations.","Have you ever driven a car in a foreign country?","Maria says she drove in France during a vacation.","John believes driving abroad requires understanding local rules.","Anna thinks it was a great experience driving in the UK.","If yes, which side of the road did they drive on?","Maria says they drove on the right side of the road.","John believes adapting to the left side in the UK was challenging.","Anna thinks driving on the left in Australia was interesting.","Were the road signs different?","Maria says some signs were different but easy to understand.","John believes learning new road signs was part of the fun.","Anna thinks road signs were mostly similar with a few exceptions.","Are the drivers in your area good drivers?","Maria says most drivers in her area follow the rules.","John believes there are many reckless drivers in his area.","Anna thinks driving habits vary widely in her city.","Do you know anything about repairing or maintaining a car?","Maria says she knows basic maintenance like oil changes.","John believes understanding car mechanics is useful.","Anna thinks she prefers taking her car to a professional for repairs.","What do you know how to do?","Maria says she can change a tire and check fluid levels.","John believes he can perform basic engine checks.","Anna thinks she is good at keeping her car clean and well-maintained.","Where did you learn how to do this?","Maria says her father taught her basic car maintenance.","John believes learning from online tutorials is helpful.","Anna thinks she learned through a car maintenance workshop."],"SEO":{"seo":{"Topic":"Cars & Driving","Title":"Mastering the Road: A Comprehensive Guide to Cars and Driving","metaTitle":"Cars and Driving: \"20 Bộ câu hỏi & Trả lời | Mastering the Road: A Comprehensive Guide to Cars and Driving\"","SEO-friendly-URL":"/comprehensive-guide-to-cars-and-driving","metaDescription":"Explore everything about cars and driving, from learning to drive to car maintenance. Discover the pros and cons of car ownership, driving safety tips, and more.","keywords":["cars","driving","car maintenance","driving safety","manual vs automatic"]},"cssStyles":{"title":{"fontWeight":"bold","fontSize":"1.5em","marginBottom":"10px"},"question":{"fontWeight":"bold","fontSize":"1.2em","marginTop":"10px"},"answer":{"marginLeft":"20px","fontSize":"1em","marginBottom":"10px"}},"contentArray":[{"content":"Why Studying Cars and Driving is Important","cssClass":"title","tag":"div"},{"content":"Cars and driving are integral aspects of modern life, impacting daily commutes, travel, and even economic activities. Studying cars and driving is important for several reasons. Firstly, understanding the mechanics and maintenance of cars can save time and money, ensuring that vehicles run efficiently and safely. Knowledge of car maintenance, such as how to change a tire or check oil levels, empowers individuals to handle minor issues independently, reducing reliance on mechanics for every small problem. Secondly, learning to drive and understanding driving laws are essential for personal freedom and mobility. Driving skills open up opportunities for travel and employment, particularly in areas where public transportation is limited. Furthermore, knowing the pros and cons of car ownership helps individuals make informed decisions about whether owning a car is the right choice for them, considering factors like cost, convenience, and environmental impact. Additionally, studying driving safety and best practices can prevent accidents and save lives. Safe driving habits, awareness of road conditions, and understanding traffic signs are crucial for reducing the risk of accidents. Lastly, exploring the differences between manual and automatic cars, and the cultural variations in driving practices, broadens our perspective and adaptability in different driving environments. Overall, a comprehensive understanding of cars and driving enhances our independence, safety, and capability to manage one of the most common modes of transportation in the world.","cssClass":"answer","tag":"div"}]},"HDTB":{"IF":{"IFname":"Q & A","IFimg":"https://i.postimg.cc/x1K5Y5PJ/info-table.jpg"},"HD":[{"HD-01":"How old were you when you first learned to drive?","HD-02":"Maria says she was 18 when she first learned to drive.","HD-03":"John believes learning to drive at 16 was the perfect age.","HD-04":"Anna thinks starting at 20 gave her more confidence."},{"HD-01":"Was there anything difficult about learning to drive?","HD-02":"Maria says parking was the most challenging part.","HD-03":"John believes understanding traffic rules was difficult.","HD-04":"Anna thinks controlling the clutch in a manual car was hard."},{"HD-01":"Can you drive a car?","HD-02":"Maria says she can drive both manual and automatic cars.","HD-03":"John believes he is a skilled driver in all conditions.","HD-04":"Anna thinks driving is a necessary skill for independence."},{"HD-01":"Can you drive a manual shift car?","HD-02":"Maria says she learned to drive a manual car first.","HD-03":"John believes manual cars are more engaging to drive.","HD-04":"Anna thinks automatic cars are more convenient, but she can drive manual too."},{"HD-01":"Do you have a car?","HD-02":"Maria says she owns a small sedan.","HD-03":"John believes having a car is essential for daily commuting.","HD-04":"Anna thinks owning a car gives her freedom to travel anytime."},{"HD-01":"What kind of car do you have?","HD-02":"Maria says she has a compact car for city driving.","HD-03":"John believes his SUV is perfect for long trips.","HD-04":"Anna thinks her hybrid car is great for the environment."},{"HD-01":"Is it a standard (manual shift) or automatic shift?","HD-02":"Maria says her car is automatic.","HD-03":"John believes manual shift cars offer better control.","HD-04":"Anna thinks automatic cars are easier to drive in traffic."},{"HD-01":"Which do you like best, a standard or automatic shift car?","HD-02":"Maria says she prefers automatic for convenience.","HD-03":"John believes standard cars are more fun to drive.","HD-04":"Anna thinks automatic is better for city driving, but standard is great for the highway."},{"HD-01":"What are the advantages of owning a car?","HD-02":"Maria says having a car provides convenience and flexibility.","HD-03":"John believes owning a car saves time on commuting.","HD-04":"Anna thinks a car is essential for traveling long distances comfortably."},{"HD-01":"What are the disadvantages of owning a car?","HD-02":"Maria says maintenance and fuel costs are significant disadvantages.","HD-03":"John believes traffic and parking issues are major problems.","HD-04":"Anna thinks the environmental impact is a concern."},{"HD-01":"Are you a good driver?","HD-02":"Maria says she considers herself a cautious driver.","HD-03":"John believes he is a confident and skilled driver.","HD-04":"Anna thinks she is a safe and responsible driver."},{"HD-01":"Have you ever been in a car accident?","HD-02":"Maria says she had a minor accident last year.","HD-03":"John believes accidents are sometimes unavoidable despite careful driving.","HD-04":"Anna thinks defensive driving can prevent most accidents."},{"HD-01":"Have you ever been pulled over by the police? What happened?","HD-02":"Maria says she was once pulled over for speeding.","HD-03":"John believes following traffic rules can avoid such incidents.","HD-04":"Anna thinks being respectful to the police helps in such situations."},{"HD-01":"Have you ever driven a car in a foreign country?","HD-02":"Maria says she drove in France during a vacation.","HD-03":"John believes driving abroad requires understanding local rules.","HD-04":"Anna thinks it was a great experience driving in the UK."},{"HD-01":"If yes, which side of the road did they drive on?","HD-02":"Maria says they drove on the right side of the road.","HD-03":"John believes adapting to the left side in the UK was challenging.","HD-04":"Anna thinks driving on the left in Australia was interesting."},{"HD-01":"Were the road signs different?","HD-02":"Maria says some signs were different but easy to understand.","HD-03":"John believes learning new road signs was part of the fun.","HD-04":"Anna thinks road signs were mostly similar with a few exceptions."},{"HD-01":"Are the drivers in your area good drivers?","HD-02":"Maria says most drivers in her area follow the rules.","HD-03":"John believes there are many reckless drivers in his area.","HD-04":"Anna thinks driving habits vary widely in her city."},{"HD-01":"Do you know anything about repairing or maintaining a car?","HD-02":"Maria says she knows basic maintenance like oil changes.","HD-03":"John believes understanding car mechanics is useful.","HD-04":"Anna thinks she prefers taking her car to a professional for repairs."},{"HD-01":"What do you know how to do?","HD-02":"Maria says she can change a tire and check fluid levels.","HD-03":"John believes he can perform basic engine checks.","HD-04":"Anna thinks she is good at keeping her car clean and well-maintained."},{"HD-01":"Where did you learn how to do this?","HD-02":"Maria says her father taught her basic car maintenance.","HD-03":"John believes learning from online tutorials is helpful.","HD-04":"Anna thinks she learned through a car maintenance workshop."}],"TB":[]},"charactor":[{"gender":"female","img":"https://i.postimg.cc/wBNmZTY8/Sarah-27.jpg","fsp":"Maria, How old were you when you first learned to drive?","data":[{"qs":["Anna thinks starting at 20 gave her more confidence."],"action":["FN01"]}],"submit":["FN01"]},{"gender":"female","img":"https://i.postimg.cc/wBNmZTY8/Sarah-27.jpg","fsp":"Maria, What kind of car do you have?","data":[{"qs":["Anna thinks her hybrid car is great for the environment."],"action":["FN01"]}],"submit":["FN01"]},{"gender":"female","img":"https://i.postimg.cc/vTh9hqF4/Emily-21.jpg","fsp":"Maria, How old were you when you first learned to drive?","data":[{"qs":["Maria says she was 18 when she first learned to drive."],"action":["FN01"]}],"submit":["FN01"]},{"gender":"female","img":"https://i.postimg.cc/wBNmZTY8/Sarah-27.jpg","fsp":"Maria, Was there anything difficult about learning to drive?","data":[{"qs":["Anna thinks controlling the clutch in a manual car was hard."],"action":["FN01"]}],"submit":["FN01"]},{"gender":"female","img":"https://i.postimg.cc/wBNmZTY8/Sarah-27.jpg","fsp":"Maria, What are the advantages of owning a car?","data":[{"qs":["Anna thinks a car is essential for traveling long distances comfortably."],"action":["FN01"]}],"submit":["FN01"]},{"gender":"female","img":"https://i.postimg.cc/KzXn83D8/Andrew-40.jpg","fsp":"Maria, Were the road signs different?","data":[{"qs":["John believes learning new road signs was part of the fun."],"action":["FN01"]}],"submit":["FN01"]},{"gender":"female","img":"https://i.postimg.cc/KzXn83D8/Andrew-40.jpg","fsp":"Maria, Can you drive a car?","data":[{"qs":["John believes he is a skilled driver in all conditions."],"action":["FN01"]}],"submit":["FN01"]},{"gender":"female","img":"https://i.postimg.cc/wBNmZTY8/Sarah-27.jpg","fsp":"Maria, Do you know anything about repairing or maintaining a car?","data":[{"qs":["Anna thinks she prefers taking her car to a professional for repairs."],"action":["FN01"]}],"submit":["FN01"]},{"gender":"female","img":"https://i.postimg.cc/KzXn83D8/Andrew-40.jpg","fsp":"Maria, What kind of car do you have?","data":[{"qs":["John believes his SUV is perfect for long trips."],"action":["FN01"]}],"submit":["FN01"]},{"gender":"female","img":"https://i.postimg.cc/vTh9hqF4/Emily-21.jpg","fsp":"Maria, Have you ever been pulled over by the police? What happened?","data":[{"qs":["Maria says she was once pulled over for speeding."],"action":["FN01"]}],"submit":["FN01"]},{"gender":"female","img":"https://i.postimg.cc/wBNmZTY8/Sarah-27.jpg","fsp":"Maria, Where did you learn how to do this?","data":[{"qs":["Anna thinks she learned through a car maintenance workshop."],"action":["FN01"]}],"submit":["FN01"]},{"gender":"female","img":"https://i.postimg.cc/wBNmZTY8/Sarah-27.jpg","fsp":"Maria, What do you know how to do?","data":[{"qs":["Anna thinks she is good at keeping her car clean and well-maintained."],"action":["FN01"]}],"submit":["FN01"]},{"gender":"female","img":"https://i.postimg.cc/KzXn83D8/Andrew-40.jpg","fsp":"Maria, Can you drive a manual shift car?","data":[{"qs":["John believes manual cars are more engaging to drive."],"action":["FN01"]}],"submit":["FN01"]},{"gender":"female","img":"https://i.postimg.cc/wBNmZTY8/Sarah-27.jpg","fsp":"Maria, Are the drivers in your area good drivers?","data":[{"qs":["Anna thinks driving habits vary widely in her city."],"action":["FN01"]}],"submit":["FN01"]},{"gender":"female","img":"https://i.postimg.cc/KzXn83D8/Andrew-40.jpg","fsp":"Maria, Have you ever been pulled over by the police? What happened?","data":[{"qs":["John believes following traffic rules can avoid such incidents."],"action":["FN01"]}],"submit":["FN01"]},{"gender":"female","img":"https://i.postimg.cc/KzXn83D8/Andrew-40.jpg","fsp":"Maria, Have you ever been in a car accident?","data":[{"qs":["John believes accidents are sometimes unavoidable despite careful driving."],"action":["FN01"]}],"submit":["FN01"]},{"gender":"female","img":"https://i.postimg.cc/vTh9hqF4/Emily-21.jpg","fsp":"Maria, Can you drive a manual shift car?","data":[{"qs":["Maria says she learned to drive a manual car first."],"action":["FN01"]}],"submit":["FN01"]},{"gender":"female","img":"https://i.postimg.cc/KzXn83D8/Andrew-40.jpg","fsp":"Maria, Do you have a car?","data":[{"qs":["John believes having a car is essential for daily commuting."],"action":["FN01"]}],"submit":["FN01"]},{"gender":"female","img":"https://i.postimg.cc/vTh9hqF4/Emily-21.jpg","fsp":"Maria, Have you ever been in a car accident?","data":[{"qs":["Maria says she had a minor accident last year."],"action":["FN01"]}],"submit":["FN01"]},{"gender":"female","img":"https://i.postimg.cc/wBNmZTY8/Sarah-27.jpg","fsp":"Maria, What are the disadvantages of owning a car?","data":[{"qs":["Anna thinks the environmental impact is a concern."],"action":["FN01"]}],"submit":["FN01"]},{"gender":"female","img":"https://i.postimg.cc/KzXn83D8/Andrew-40.jpg","fsp":"Maria, What are the disadvantages of owning a car?","data":[{"qs":["John believes traffic and parking issues are major problems."],"action":["FN01"]}],"submit":["FN01"]},{"gender":"female","img":"https://i.postimg.cc/vTh9hqF4/Emily-21.jpg","fsp":"Maria, Where did you learn how to do this?","data":[{"qs":["Maria says her father taught her basic car maintenance."],"action":["FN01"]}],"submit":["FN01"]},{"gender":"female","img":"https://i.postimg.cc/vTh9hqF4/Emily-21.jpg","fsp":"Maria, What are the disadvantages of owning a car?","data":[{"qs":["Maria says maintenance and fuel costs are significant disadvantages."],"action":["FN01"]}],"submit":["FN01"]},{"gender":"female","img":"https://i.postimg.cc/vTh9hqF4/Emily-21.jpg","fsp":"Maria, Do you have a car?","data":[{"qs":["Maria says she owns a small sedan."],"action":["FN01"]}],"submit":["FN01"]},{"gender":"female","img":"https://i.postimg.cc/KzXn83D8/Andrew-40.jpg","fsp":"Maria, Which do you like best, a standard or automatic shift car?","data":[{"qs":["John believes standard cars are more fun to drive."],"action":["FN01"]}],"submit":["FN01"]},{"gender":"female","img":"https://i.postimg.cc/vTh9hqF4/Emily-21.jpg","fsp":"Maria, What kind of car do you have?","data":[{"qs":["Maria says she has a compact car for city driving."],"action":["FN01"]}],"submit":["FN01"]},{"gender":"female","img":"https://i.postimg.cc/vTh9hqF4/Emily-21.jpg","fsp":"Maria, Are the drivers in your area good drivers?","data":[{"qs":["Maria says most drivers in her area follow the rules."],"action":["FN01"]}],"submit":["FN01"]},{"gender":"female","img":"https://i.postimg.cc/wBNmZTY8/Sarah-27.jpg","fsp":"Maria, Do you have a car?","data":[{"qs":["Anna thinks owning a car gives her freedom to travel anytime."],"action":["FN01"]}],"submit":["FN01"]},{"gender":"female","img":"https://i.postimg.cc/wBNmZTY8/Sarah-27.jpg","fsp":"Maria, Were the road signs different?","data":[{"qs":["Anna thinks road signs were mostly similar with a few exceptions."],"action":["FN01"]}],"submit":["FN01"]},{"gender":"female","img":"https://i.postimg.cc/vTh9hqF4/Emily-21.jpg","fsp":"Maria, What are the advantages of owning a car?","data":[{"qs":["Maria says having a car provides convenience and flexibility."],"action":["FN01"]}],"submit":["FN01"]},{"gender":"female","img":"https://i.postimg.cc/KzXn83D8/Andrew-40.jpg","fsp":"Maria, Have you ever driven a car in a foreign country?","data":[{"qs":["John believes driving abroad requires understanding local rules."],"action":["FN01"]}],"submit":["FN01"]},{"gender":"female","img":"https://i.postimg.cc/wBNmZTY8/Sarah-27.jpg","fsp":"Maria, Can you drive a car?","data":[{"qs":["Anna thinks driving is a necessary skill for independence."],"action":["FN01"]}],"submit":["FN01"]},{"gender":"female","img":"https://i.postimg.cc/wBNmZTY8/Sarah-27.jpg","fsp":"Maria, Can you drive a manual shift car?","data":[{"qs":["Anna thinks automatic cars are more convenient, but she can drive manual too."],"action":["FN01"]}],"submit":["FN01"]},{"gender":"female","img":"https://i.postimg.cc/KzXn83D8/Andrew-40.jpg","fsp":"Maria, How old were you when you first learned to drive?","data":[{"qs":["John believes learning to drive at 16 was the perfect age."],"action":["FN01"]}],"submit":["FN01"]},{"gender":"female","img":"https://i.postimg.cc/vTh9hqF4/Emily-21.jpg","fsp":"Maria, Can you drive a car?","data":[{"qs":["Maria says she can drive both manual and automatic cars."],"action":["FN01"]}],"submit":["FN01"]},{"gender":"female","img":"https://i.postimg.cc/wBNmZTY8/Sarah-27.jpg","fsp":"Maria, Which do you like best, a standard or automatic shift car?","data":[{"qs":["Anna thinks automatic is better for city driving, but standard is great for the highway."],"action":["FN01"]}],"submit":["FN01"]},{"gender":"female","img":"https://i.postimg.cc/vTh9hqF4/Emily-21.jpg","fsp":"Maria, Are you a good driver?","data":[{"qs":["Maria says she considers herself a cautious driver."],"action":["FN01"]}],"submit":["FN01"]},{"gender":"female","img":"https://i.postimg.cc/KzXn83D8/Andrew-40.jpg","fsp":"Maria, Are the drivers in your area good drivers?","data":[{"qs":["John believes there are many reckless drivers in his area."],"action":["FN01"]}],"submit":["FN01"]},{"gender":"female","img":"https://i.postimg.cc/wBNmZTY8/Sarah-27.jpg","fsp":"Maria, Have you ever driven a car in a foreign country?","data":[{"qs":["Anna thinks it was a great experience driving in the UK."],"action":["FN01"]}],"submit":["FN01"]},{"gender":"female","img":"https://i.postimg.cc/KzXn83D8/Andrew-40.jpg","fsp":"Maria, If yes, which side of the road did they drive on?","data":[{"qs":["John believes adapting to the left side in the UK was challenging."],"action":["FN01"]}],"submit":["FN01"]},{"gender":"female","img":"https://i.postimg.cc/vTh9hqF4/Emily-21.jpg","fsp":"Maria, Have you ever driven a car in a foreign country?","data":[{"qs":["Maria says she drove in France during a vacation."],"action":["FN01"]}],"submit":["FN01"]},{"gender":"female","img":"https://i.postimg.cc/vTh9hqF4/Emily-21.jpg","fsp":"Maria, Was there anything difficult about learning to drive?","data":[{"qs":["Maria says parking was the most challenging part."],"action":["FN01"]}],"submit":["FN01"]},{"gender":"female","img":"https://i.postimg.cc/wBNmZTY8/Sarah-27.jpg","fsp":"Maria, Is it a standard (manual shift) or automatic shift?","data":[{"qs":["Anna thinks automatic cars are easier to drive in traffic."],"action":["FN01"]}],"submit":["FN01"]},{"gender":"female","img":"https://i.postimg.cc/KzXn83D8/Andrew-40.jpg","fsp":"Maria, What are the advantages of owning a car?","data":[{"qs":["John believes owning a car saves time on commuting."],"action":["FN01"]}],"submit":["FN01"]},{"gender":"female","img":"https://i.postimg.cc/KzXn83D8/Andrew-40.jpg","fsp":"Maria, Do you know anything about repairing or maintaining a car?","data":[{"qs":["John believes understanding car mechanics is useful."],"action":["FN01"]}],"submit":["FN01"]},{"gender":"female","img":"https://i.postimg.cc/vTh9hqF4/Emily-21.jpg","fsp":"Maria, Which do you like best, a standard or automatic shift car?","data":[{"qs":["Maria says she prefers automatic for convenience."],"action":["FN01"]}],"submit":["FN01"]},{"gender":"female","img":"https://i.postimg.cc/vTh9hqF4/Emily-21.jpg","fsp":"Maria, Is it a standard (manual shift) or automatic shift?","data":[{"qs":["Maria says her car is automatic."],"action":["FN01"]}],"submit":["FN01"]},{"gender":"female","img":"https://i.postimg.cc/wBNmZTY8/Sarah-27.jpg","fsp":"Maria, Have you ever been in a car accident?","data":[{"qs":["Anna thinks defensive driving can prevent most accidents."],"action":["FN01"]}],"submit":["FN01"]},{"gender":"female","img":"https://i.postimg.cc/vTh9hqF4/Emily-21.jpg","fsp":"Maria, What do you know how to do?","data":[{"qs":["Maria says she can change a tire and check fluid levels."],"action":["FN01"]}],"submit":["FN01"]},{"gender":"female","img":"https://i.postimg.cc/wBNmZTY8/Sarah-27.jpg","fsp":"Maria, Are you a good driver?","data":[{"qs":["Anna thinks she is a safe and responsible driver."],"action":["FN01"]}],"submit":["FN01"]},{"gender":"female","img":"https://i.postimg.cc/vTh9hqF4/Emily-21.jpg","fsp":"Maria, Were the road signs different?","data":[{"qs":["Maria says some signs were different but easy to understand."],"action":["FN01"]}],"submit":["FN01"]},{"gender":"female","img":"https://i.postimg.cc/wBNmZTY8/Sarah-27.jpg","fsp":"Maria, If yes, which side of the road did they drive on?","data":[{"qs":["Anna thinks driving on the left in Australia was interesting."],"action":["FN01"]}],"submit":["FN01"]},{"gender":"female","img":"https://i.postimg.cc/KzXn83D8/Andrew-40.jpg","fsp":"Maria, Is it a standard (manual shift) or automatic shift?","data":[{"qs":["John believes manual shift cars offer better control."],"action":["FN01"]}],"submit":["FN01"]},{"gender":"female","img":"https://i.postimg.cc/KzXn83D8/Andrew-40.jpg","fsp":"Maria, Where did you learn how to do this?","data":[{"qs":["John believes learning from online tutorials is helpful."],"action":["FN01"]}],"submit":["FN01"]},{"gender":"female","img":"https://i.postimg.cc/vTh9hqF4/Emily-21.jpg","fsp":"Maria, If yes, which side of the road did they drive on?","data":[{"qs":["Maria says they drove on the right side of the road."],"action":["FN01"]}],"submit":["FN01"]},{"gender":"female","img":"https://i.postimg.cc/KzXn83D8/Andrew-40.jpg","fsp":"Maria, What do you know how to do?","data":[{"qs":["John believes he can perform basic engine checks."],"action":["FN01"]}],"submit":["FN01"]},{"gender":"female","img":"https://i.postimg.cc/KzXn83D8/Andrew-40.jpg","fsp":"Maria, Was there anything difficult about learning to drive?","data":[{"qs":["John believes understanding traffic rules was difficult."],"action":["FN01"]}],"submit":["FN01"]},{"gender":"female","img":"https://i.postimg.cc/vTh9hqF4/Emily-21.jpg","fsp":"Maria, Do you know anything about repairing or maintaining a car?","data":[{"qs":["Maria says she knows basic maintenance like oil changes."],"action":["FN01"]}],"submit":["FN01"]},{"gender":"female","img":"https://i.postimg.cc/wBNmZTY8/Sarah-27.jpg","fsp":"Maria, Have you ever been pulled over by the police? What happened?","data":[{"qs":["Anna thinks being respectful to the police helps in such situations."],"action":["FN01"]}],"submit":["FN01"]},{"gender":"female","img":"https://i.postimg.cc/KzXn83D8/Andrew-40.jpg","fsp":"Maria, Are you a good driver?","data":[{"qs":["John believes he is a confident and skilled driver."],"action":["FN01"]}],"submit":["FN01"]}]}]